Workbook

Sheet Raw Data
A1: Annual Report Of | F1: Annual Data Of
A2: Square Pharmaceuticals | B2: Column1 | C2: Column2 | F2: Ibna Sina Pharmaceuticals | G2: Column1 | H2: Column2
A3: Item | B3: 2024 | C3: 2023 | F3: Item | G3: 2024 | H3: 2023
A4: Non Current Asset | B4: 42273928338 | C4: 34585613547 | F4: Non Current Asset | G4: 3888791104 | H4: 3169096180
A5: Current Assets | B5: 69735986410 | C5: 70169514926 | F5: Current Asset | G5: 2620323446 | H5: 1836444762
A6: Total Assets | B6: =SUM(B4,B5) -> 112009914748 | C6: =SUM(C4,C5) -> 104755128473 | F6: Total Asset | G6: =SUM(G4:G5) -> 6509114550 | H6: =SUM(H4:H5) -> 5005540942
A7: Current Liabilities | B7: 5589045579 | C7: 3212077810 | F7: Current Liabilities | G7: 2318099470 | H7: 1461481620
A8: Non Current liabilities | B8: 625749549 | C8: 1026086605 | F8: Non Current Liabilities | G8: 657654587 | H8: 488243171
A9: Total Liabilities | B9: =SUM(B7:B8) -> 6214795128 | C9: =SUM(C7:C8) -> 4238164415 | F9: Total Liabilities | G9: =SUM(G7:G8) -> 2975754057 | H9: =SUM(H7:H8) -> 1949724791
A10: Total Equity | B10: 105795119620 | C10: 100516964058 | F10: Total Equity | G10: 3533360493 | H10: 3055816151
A11: Total Equity and Liablities | B11: =SUM(B9:B10) -> 112009914748 | C11: =SUM(C9:C10) -> 104755128473 | F11: Total Equity and Liabilities | G11: =SUM(G9:G10) -> 6509114550 | H11: =SUM(H9:H10) -> 5005540942
A12: Cash and Cash Equivalents | B12: 52305603356 | C12: 50079192249 | F12: Revenue | G12: 11370922344 | H12: 9125331307
A13: Net Revenue | B13: 59794584816 | C13: 58419084978 | F13: Gross Profit | G13: 4531507148 | H13: 3871099631
A14: Gross Profit | B14: 27267821084 | C14: 28034308091 | F14: Operating Profit | G14: 960060692 | H14: 860364720
A15: Operating Income | B15: 15960600763 | C15: 17874695253 | F15: Profit Before Tax | G15: 894698822 | H15: 804731983
A16: Profit before Tax | B16: 19887843068 | C16: 21097122423 | F16: Net Profit | G16: 671350473 | H16: 605808719
A17: Net Profit | B17: 15591371906 | C17: 16470227513 | F17: Cash and Cash Equivalents | G17: 365229893 | H17: 365229893
A18: Finance Cost | B18: 27943 | C18: 21966 | F18: Finance Cost ( Interest Expense) | G18: 53580520 | H18: 44431461
A19: 886,451,010 ordinary shares od Tk.10 each full paid up | B19: 8864510100 | C19: 8864510100 | F19: 31,243,627 Ordinary Shares of Tk. 10 each fully paid up in cash | G19: 312436270 | H19: 312436270
A20: Ordinary Share Outstandings ( Unit) | B20: 886451010 | C20: 886451010 | F20: Ordinary Share Outstandings (Unit) | G20: 31243627 | H20: 31243627

Sheet Ratio Calculation
A1: Ratio Analysis of Square Pharmaceuticals | G1: Ratio Analysis Of Ibna Sina Pharmaceuticals
A2: Ratio | B2: Formula | C2: 2024 | D2: 2023 | G2: Ratio | H2: Formula | I2: 2024 | J2: 2023
A3: Current Ratio | B3: Current Asset/ Current Liabilities | C3: ='Raw Data'!B5/'Raw Data'!B7 -> 12.477262 | D3: ='Raw Data'!C5/'Raw Data'!C7 -> 21.845522 | G3: Current Ratio | H3: Current Asset/ Current Liabilities | I3: ='Raw Data'!G5/'Raw Data'!G7 -> 1.1303758 | J3: ='Raw Data'!H5/'Raw Data'!H7 -> 1.2565637
A4: Gross Profit Margin | B4: Gross Profit/Revenue | C4: ='Raw Data'!B14/'Raw Data'!B13 -> 0.45602493 | D4: ='Raw Data'!C14/'Raw Data'!C13 -> 0.4798827 | G4: Gross Profit Margin | H4: Gross Profit/Revenue | I4: ='Raw Data'!G13/'Raw Data'!G12 -> 0.39851711 | J4: ='Raw Data'!H13/'Raw Data'!H12 -> 0.42421469
A5: Operating Profit Margin | B5: Operating Profit/Revenue | C5: ='Raw Data'!B15/'Raw Data'!B13 -> 0.26692385 | D5: ='Raw Data'!C15/'Raw Data'!C13 -> 0.30597356 | G5: Operating Profit Margin | H5: Operating Profit/Revenue | I5: ='Raw Data'!G14/'Raw Data'!G12 -> 0.084431206 | J5: ='Raw Data'!H14/'Raw Data'!H12 -> 0.094283121
A6: Net Profit margin | B6: Net Profit/Revenue | C6: ='Raw Data'!B17/'Raw Data'!B13 -> 0.26074889 | D6: ='Raw Data'!C16/'Raw Data'!C13 -> 0.36113408 | G6: Net Profit margin | H6: Net Profit/Revenue | I6: ='Raw Data'!G16/'Raw Data'!G12 -> 0.059040987 | J6: ='Raw Data'!H16/'Raw Data'!H12 -> 0.066387586
A7: Debt Ratio | B7: Total Libailities / Total Assets | C7: ='Raw Data'!B9/'Raw Data'!B6 -> 0.05548433 | D7: ='Raw Data'!C9/'Raw Data'!C6 -> 0.040457823 | G7: Debt Ratio | H7: Total Libailities / Total Assets | I7: ='Raw Data'!G9/'Raw Data'!G6 -> 0.45716726 | J7: ='Raw Data'!H9/'Raw Data'!H6 -> 0.3895133
A8: Debt To Equity ratio | B8: Total Libailities / Total Equity | C8: ='Raw Data'!B9/'Raw Data'!B10 -> 0.058743684 | D8: ='Raw Data'!C9/'Raw Data'!C10 -> 0.042163673 | G8: Debt To Equity ratio | H8: Total Libailities / Total Equity | I8: ='Raw Data'!G9/'Raw Data'!G10 -> 0.84218807 | J8: ='Raw Data'!H9/'Raw Data'!H10 -> 0.63803733
A9: Total Asset Turnover | B9: Revenue /Total Asset | C9: ='Raw Data'!B13/'Raw Data'!B6 -> 0.53383296 | D9: ='Raw Data'!C13/'Raw Data'!C6 -> 0.55767279 | G9: Total Asset Turnover | H9: Revenue /Total Asset | I9: ='Raw Data'!G12/'Raw Data'!G6 -> 1.7469231 | J9: ='Raw Data'!H12/'Raw Data'!H6 -> 1.823046
A10: Return On Equity | B10: Net Profit/ Total Equity | C10: ='Raw Data'!B17/'Raw Data'!B10 -> 0.14737326 | D10: ='Raw Data'!C17/'Raw Data'!C10 -> 0.1638552 | G10: Return On Equity | H10: Net Profit/ Total Equity | I10: ='Raw Data'!G16/Table6[[#This Row],[Column1]] -> 0.19000339 | J10: ='Raw Data'!H16/Table6[[#This Row],[Column2]] -> 0.19824776
A11: Return ON Asset | B11: Net Profit / Total Assets | C11: ='Raw Data'!B17/'Raw Data'!B6 -> 0.13919636 | D11: ='Raw Data'!C17/'Raw Data'!C6 -> 0.15722598 | G11: Return ON Asset | H11: Net Profit / Total Assets | I11: ='Raw Data'!G16/'Raw Data'!G6 -> 0.10314006 | J11: ='Raw Data'!H16/'Raw Data'!H6 -> 0.12102762
A12: Earnig Per Share ( EPS) | B12: Net Profit / No. of Ordinary Share Outstandings | C12: ='Raw Data'!B17/'Raw Data'!B20 -> 17.588532 | D12: ='Raw Data'!C17/'Raw Data'!C20 -> 18.579964 | G12: Earning Per Share | H12: Net Profit / No. of Ordinary Share Outstandings | I12: ='Raw Data'!G16/'Raw Data'!G20 -> 21.487597 | J12: ='Raw Data'!H16/'Raw Data'!H20 -> 19.389833
A13: Equity Multiplier | B13: Total Asset/ Total Equity | C13: ='Raw Data'!B6/'Raw Data'!B10 -> 1.0587437 | D13: ='Raw Data'!C6/'Raw Data'!C10 -> 1.0421637 | G13: Equity Multiplier | H13: Total Asset/ Total Equity | I13: ='Raw Data'!G6/'Raw Data'!G10 -> 1.8421881 | J13: ='Raw Data'!H6/'Raw Data'!H10 -> 1.6380373
A14: Dupont Analysis( ROE) | B14: Net Profit Margin* Total Asset Turnover* Equity Multiplier | C14: =C6*C9*C13 -> 0.14737326 | D14: =D6*D9*D13 -> 0.20988619 | G14: Dupont Analysis (ROE) | H14: Net Profit Margin* Total Asset Turnover* Equity Multiplier | I14: =I6*I9*I13 -> 0.19000339 | J14: =J6*J9*J13 -> 0.19824776

Sheet Dashbord Data
A1: Table Of Comparison
A2: Item | B2: Square Pharma(2023) | C2: Square Pharma(2024) | D2: Ibna Sina Pharma(2023) | E2: Ibna Sina Pharma(2024)
A3: Current Ratio | B3: =Table7[[#This Row],[2023]] -> 21.845522 | C3: =Table7[[#This Row],[2024]] -> 12.477262 | D3: =Table8[[#This Row],[2023]] -> 1.2565637 | E3: =Table8[[#This Row],[2024]] -> 1.1303758
A4: Gross Profit Margin | B4: =Table7[[#This Row],[2023]] -> 0.4798827 | C4: =Table7[[#This Row],[2024]] -> 0.45602493 | D4: =Table8[[#This Row],[2023]] -> 0.42421469 | E4: =Table8[[#This Row],[2024]] -> 0.39851711
A5: Operating Profit Margin | B5: =Table7[[#This Row],[2023]] -> 0.30597356 | C5: =Table7[[#This Row],[2024]] -> 0.26692385 | D5: =Table8[[#This Row],[2023]] -> 0.094283121 | E5: =Table8[[#This Row],[2024]] -> 0.084431206 | H5: Item | I5: Square Pharma(2023) | J5: Ibna Sina Pharma(2023) | K5: Square Pharma(2024) | L5: Ibna Sina Pharma(2024)
A6: Net Profit margin | B6: =Table7[[#This Row],[2023]] -> 0.36113408 | C6: =Table7[[#This Row],[2024]] -> 0.26074889 | D6: =Table8[[#This Row],[2023]] -> 0.066387586 | E6: =Table8[[#This Row],[2024]] -> 0.059040987
A7: Debt Ratio | B7: =Table7[[#This Row],[2023]] -> 0.040457823 | C7: =Table7[[#This Row],[2024]] -> 0.05548433 | D7: =Table8[[#This Row],[2023]] -> 0.3895133 | E7: =Table8[[#This Row],[2024]] -> 0.45716726 | H7: Debt Ratio | I7: =Table7[[#This Row],[2023]] -> 0.040457823 | J7: =Table8[[#This Row],[2023]] -> 0.3895133 | K7: =Table7[[#This Row],[2024]] -> 0.05548433 | L7: 0.46
A8: Debt To Equity ratio | B8: =Table7[[#This Row],[2023]] -> 0.042163673 | C8: =Table7[[#This Row],[2024]] -> 0.058743684 | D8: =Table8[[#This Row],[2023]] -> 0.63803733 | E8: =Table8[[#This Row],[2024]] -> 0.84218807
A9: Total Asset Turnover | B9: =Table7[[#This Row],[2023]] -> 0.55767279 | C9: =Table7[[#This Row],[2024]] -> 0.53383296 | D9: =Table8[[#This Row],[2023]] -> 1.823046 | E9: =Table8[[#This Row],[2024]] -> 1.7469231
A10: Return On Equity | B10: =Table7[[#This Row],[2023]] -> 0.1638552 | C10: =Table7[[#This Row],[2024]] -> 0.14737326 | D10: =Table8[[#This Row],[2023]] -> 0.19824776 | E10: =Table8[[#This Row],[2024]] -> 0.19000339
A11: Return ON Asset | B11: =Table7[[#This Row],[2023]] -> 0.15722598 | C11: =Table7[[#This Row],[2024]] -> 0.13919636 | D11: =Table8[[#This Row],[2023]] -> 0.12102762 | E11: =Table8[[#This Row],[2024]] -> 0.10314006
A12: Earnig Per Share ( EPS) | B12: =Table7[[#This Row],[2023]] -> 18.579964 | C12: =Table7[[#This Row],[2024]] -> 17.588532 | D12: =Table8[[#This Row],[2023]] -> 19.389833 | E12: =Table8[[#This Row],[2024]] -> 21.487597 | H12: Item | I12: Square Pharma(2023) | J12: Square Pharma(2024) | K12: Ibna Sina Pharma(2023) | L12: Ibna Sina Pharma(2024)
A13: Equity Multiplier | B13: =Table7[[#This Row],[2023]] -> 1.0421637 | C13: =Table7[[#This Row],[2024]] -> 1.0587437 | D13: =Table8[[#This Row],[2023]] -> 1.6380373 | E13: =Table8[[#This Row],[2024]] -> 1.8421881 | H13: Dupont Analysis( ROE) | I13: 0.21 | J13: 0.15 | K13: 0.2 | L13: 0.19
A14: Dupont Analysis( ROE) | B14: =Table7[[#This Row],[2023]] -> 0.20988619 | C14: =Table7[[#This Row],[2024]] -> 0.14737326 | D14: =Table8[[#This Row],[2023]] -> 0.19824776 | E14: =Table8[[#This Row],[2024]] -> 0.19000339

Sheet Dashbord

Sheet Conclusion
A1: Conclusion
A2: Square pharma | C2: Ibna Sina Pharma
